pi_servo_hat.py
sparkfun_pi_servo_hat-0.9.1.dist-info/LICENSE
sparkfun_pi_servo_hat-0.9.1.dist-info/METADATA
sparkfun_pi_servo_hat-0.9.1.dist-info/WHEEL
sparkfun_pi_servo_hat-0.9.1.dist-info/top_level.txt
sparkfun_pi_servo_hat-0.9.1.dist-info/RECORD
