Metadata-Version: 2.1
Name: sparkfun_pi_servo_hat
Version: 0.9.1
Summary: SparkFun Electronics Pi Servo Hat
Home-page: https://www.sparkfun.com/products/15316
Author: SparkFun Electronics
Author-email: info@sparkfun.com
License: MIT
Keywords: electronics,maker
Platform: UNKNOWN
Classifier: Development Status :: 3 - Alpha
Classifier: Intended Audience :: Developers
Classifier: Topic :: Software Development :: Build Tools
Classifier: License :: OSI Approved :: MIT License
Classifier: Programming Language :: Python :: 2.7
Classifier: Programming Language :: Python :: 3.5
Classifier: Programming Language :: Python :: 3.6
Classifier: Programming Language :: Python :: 3.7
License-File: LICENSE
